LICENSE
MANIFEST.in
README.rst
deis.py
requirements.txt
setup.cfg
setup.py
deis.egg-info/PKG-INFO
deis.egg-info/SOURCES.txt
deis.egg-info/dependency_links.txt
deis.egg-info/entry_points.txt
deis.egg-info/requires.txt
deis.egg-info/top_level.txt
deis.egg-info/zip-safe