Metadata-Version: 1.1
Name: deis
Version: 1.9.1
Summary: Command-line Client for Deis, the open PaaS
Home-page: https://github.com/deis/deis
Author: Engine Yard
Author-email: info@deis.io
License: Copyright 2013, 2014 Engine Yard, Inc.
